datawok/__init__.py
datawok/admin.py
datawok/apps.py
datawok/celery.py
datawok/conf.py
datawok/constants.py
datawok/exceptions.py
datawok/mixins.py
datawok/routers.py
datawok/urls.py
datawok/generators/serializers.py
datawok/generators/viewsets.py
datawok/generators/views/__init__.py
datawok/generators/views/detail.py
datawok/generators/views/publish.py
datawok/generators/views/upload_csv_file.py
datawok/management/__init__.py
datawok/management/commands/__init__.py
datawok/migrations/__init__.py
datawok/models/__init__.py
datawok/models/base.py
datawok/models/get_models.py
datawok/models/meta.py
datawok/models/meta_category.py
datawok/models/query.py
datawok/serializers/__init__.py
datawok/serializers/get_serializers.py
datawok/serializers/meta.py
datawok/serializers/query.py
datawok/static/datawok/css/main.detail.css
datawok/static/datawok/css/main.list.css
datawok/static/datawok/js/main.detail.js
datawok/static/datawok/js/main.list.js
datawok/static/datawok/js/papaparse.min.js
datawok/tasks/__init__.py
datawok/tasks/aws.py
datawok/templates/datawok/base.html
datawok/templates/datawok/detail.html
datawok/templates/datawok/home.html
datawok/templates/datawok/list.html
datawok/templates/datawok/nav.html
datawok/utils/__init__.py
datawok/utils/api_auth.py
datawok/utils/auth.py
datawok/utils/aws.py
datawok/utils/flatten.py
datawok/utils/get_field_type.py
datawok/utils/get_model_by_name.py
datawok/utils/importers.py
datawok/utils/process_input_data.py
datawok/views/__init__.py
datawok/views/base.py
datawok/views/get_views.py
datawok/views/list.py
datawok/views/sql.py
datawok/viewsets/__init__.py
datawok/viewsets/get_viewsets.py
datawok/viewsets/meta.py
datawok/viewsets/query.py
django_datawok-0.0.7.dist-info/METADATA
django_datawok-0.0.7.dist-info/RECORD
django_datawok-0.0.7.dist-info/WHEEL
django_datawok-0.0.7.dist-info/top_level.txt
